{
  "hash": "a84fab6f",
  "configHash": "f347b4f5",
  "lockfileHash": "d4b31733",
  "browserHash": "2b7dff63",
  "optimized": {
    "react": {
      "src": "../../node_modules/react/index.js",
      "file": "react.js",
      "fileHash": "d586c56b",
      "needsInterop": true
    },
    "react-dom/client": {
      "src": "../../node_modules/react-dom/client.js",
      "file": "react-dom_client.js",
      "fileHash": "3872775a",
      "needsInterop": true
    },
    "react-router-dom": {
      "src": "../../node_modules/react-router-dom/dist/index.js",
      "file": "react-router-dom.js",
      "fileHash": "30ac9fd1",
      "needsInterop": false
    },
    "@tanstack/react-query": {
      "src": "../../node_modules/@tanstack/react-query/build/modern/index.js",
      "file": "@tanstack_react-query.js",
      "fileHash": "31b780ab",
      "needsInterop": false
    },
    "react-i18next": {
      "src": "../../node_modules/react-i18next/dist/es/index.js",
      "file": "react-i18next.js",
      "fileHash": "70e4ee63",
      "needsInterop": false
    },
    "i18next": {
      "src": "../../node_modules/i18next/dist/esm/i18next.js",
      "file": "i18next.js",
      "fileHash": "680ff1c6",
      "needsInterop": false
    },
    "prop-types": {
      "src": "../../node_modules/prop-types/index.js",
      "file": "prop-types.js",
      "fileHash": "1eeb452a",
      "needsInterop": true
    },
    "axios": {
      "src": "../../node_modules/axios/index.js",
      "file": "axios.js",
      "fileHash": "8ae61b8a",
      "needsInterop": false
    },
    "dompurify": {
      "src": "../../node_modules/dompurify/dist/purify.es.mjs",
      "file": "dompurify.js",
      "fileHash": "ec997710",
      "needsInterop": false
    },
    "marked": {
      "src": "../../node_modules/marked/lib/marked.esm.js",
      "file": "marked.js",
      "fileHash": "9a61a50d",
      "needsInterop": false
    }
  },
  "chunks": {
    "chunk-PV7ZWGTI": {
      "file": "chunk-PV7ZWGTI.js"
    },
    "chunk-2CLD7BNN": {
      "file": "chunk-2CLD7BNN.js"
    },
    "chunk-WOOG5QLI": {
      "file": "chunk-WOOG5QLI.js"
    }
  }
}